femr_oldcpu-0.1.16.dist-info/WHEEL
femr_oldcpu-0.1.16.dist-info/LICENSE
femr_oldcpu-0.1.16.dist-info/RECORD
femr_oldcpu-0.1.16.dist-info/entry_points.txt
femr_oldcpu-0.1.16.dist-info/top_level.txt
femr_oldcpu-0.1.16.dist-info/METADATA
femr/jax.py
femr/extension.pypy39-pp73-x86_64-linux-gnu.so
femr/__init__.py
femr/extractors/omop.py
femr/extractors/csv.py
femr/extractors/__init__.py
femr/featurizers/core.py
femr/featurizers/featurizers_notes.py
femr/featurizers/utils.py
femr/featurizers/featurizers.py
femr/featurizers/__init__.py
femr/etl_pipelines/omop.py
femr/etl_pipelines/simple.py
femr/etl_pipelines/sickkids.py
femr/etl_pipelines/stanford.py
femr/etl_pipelines/__init__.py
femr/etl_pipelines/mimic.py
femr/models/scripts.py
femr/models/linear_probe.py
femr/models/__init__.py
femr/models/transformer.py
femr/models/dataloader.py
femr/labelers/omop.py
femr/labelers/core.py
femr/labelers/omop_inpatient_admissions.py
femr/labelers/omop_lab_values.py
femr/labelers/__init__.py
femr/extension/__init__.pyi
femr/extension/jax.pyi
femr/extension/datasets.pyi
femr/datasets/types.py
femr/datasets/fileio.py
femr/datasets/__init__.py
femr/metrics/__init__.py
femr/transforms/sickkids.py
femr/transforms/stanford.py
femr/transforms/__init__.py
femr/transforms/mimic.py
femr/transforms/notes.py
